cryptowatch/__init__.py
cryptowatch/__main__.py
cryptowatch/auth.py
cryptowatch/errors.py
cryptowatch/requestor.py
cryptowatch/utils.py
cryptowatch/resources/__init__.py
cryptowatch/resources/allowance.py
cryptowatch/resources/assets.py
cryptowatch/resources/base.py
cryptowatch/resources/exchanges.py
cryptowatch/resources/instruments.py
cryptowatch/resources/markets.py
cryptowatch/stream/__init__.py
cryptowatch/stream/proto/public/broker/broker_pb2.py
cryptowatch/stream/proto/public/broker/private_pb2.py
cryptowatch/stream/proto/public/client/client_pb2.py
cryptowatch/stream/proto/public/markets/asset_pb2.py
cryptowatch/stream/proto/public/markets/index_pb2.py
cryptowatch/stream/proto/public/markets/market_pb2.py
cryptowatch/stream/proto/public/markets/pair_pb2.py
cryptowatch/stream/proto/public/stream/stream_pb2.py
cryptowatch_sdk-0.1.0.dist-info/LICENSE
cryptowatch_sdk-0.1.0.dist-info/METADATA
cryptowatch_sdk-0.1.0.dist-info/WHEEL
cryptowatch_sdk-0.1.0.dist-info/entry_points.txt
cryptowatch_sdk-0.1.0.dist-info/top_level.txt
cryptowatch_sdk-0.1.0.dist-info/RECORD
