Metadata-Version: 2.1
Name: cryptowatch-sdk
Version: 0.1.0
Summary: Python bindings for the Cryptowatch API. Cryptocurrency markets, assets, instruments and exchanges data.
Home-page: https://github.com/cryptowatch/cw-sdk-python
Author: Cryptowatch
Author-email: infra@cryptowat.ch
License: BSD-2
Project-URL: Bug Tracker, https://github.com/cryptowatch/cw-sdk-python/issues
Project-URL: Documentation, https://github.com/cryptowatch/cw-sdk-python#installation
Project-URL: Source Code, https://github.com/cryptowatch/cw-sdk-python
Keywords: cryptowatch sdk bitcoin crypto
Classifier: Intended Audience :: Developers
Classifier: Topic :: Office/Business :: Financial
Classifier: Topic :: Office/Business :: Financial :: Investment
Classifier: Intended Audience :: Financial and Insurance Industry
Classifier: License :: OSI Approved :: BSD License
Classifier: Programming Language :: Python :: 3.7
Requires-Python: >=3.7
License-File: LICENSE
Requires-Dist: marshmallow (==3.13.0)
Requires-Dist: requests (==2.25.1)
Requires-Dist: PyYAML (>=5.4)
Requires-Dist: urllib3 (>=1.26.5)
Requires-Dist: websocket-client (>=1.0.0)
Requires-Dist: protobuf (>=3.11.3)
